linreg_add2/finalized_model2.pickle
linreg_add2/linreg.py
linreg_add2-1.0.5.dist-info/LICENSE.txt
linreg_add2-1.0.5.dist-info/METADATA
linreg_add2-1.0.5.dist-info/WHEEL
linreg_add2-1.0.5.dist-info/top_level.txt
linreg_add2-1.0.5.dist-info/RECORD
