Metadata-Version: 2.1
Name: linreg-add2
Version: 1.0.5
Summary: A Python package to predict addmission chances using gre score tofel score and other details
Home-page: https://github.com/DexDand/linreg-add
Author: Abhishek Dand
Author-email: abhi080497@gmail.com
License: MIT
Platform: UNKNOWN
Classifier: License :: OSI Approved :: MIT License
Classifier: Programming Language :: Python :: 3
Classifier: Programming Language :: Python :: 3.7
